tpyfilestructure/__init__.py
tpyfilestructure/__main__.py
tpyfilestructure-0.0.1.dist-info/METADATA
tpyfilestructure-0.0.1.dist-info/WHEEL
tpyfilestructure-0.0.1.dist-info/entry_points.txt
tpyfilestructure-0.0.1.dist-info/top_level.txt
tpyfilestructure-0.0.1.dist-info/RECORD
