Metadata-Version: 2.1
Name: tpyfilestructure
Version: 0.0.1
Summary: Python package to read and display the file/folder names present in a directory
Home-page: https://github.com/tarun571999/tpyfilestructure
Author: Tharun Kumar T
Author-email: tarunkumar571999@gmail.com
License: MIT
Platform: UNKNOWN
Classifier: License :: OSI Approved :: MIT License
Classifier: Programming Language :: Python :: 3
Requires-Python: >=3.7
